processio/__init__.py
processio-1.2.0.dist-info/LICENSE
processio-1.2.0.dist-info/METADATA
processio-1.2.0.dist-info/WHEEL
processio-1.2.0.dist-info/top_level.txt
processio-1.2.0.dist-info/RECORD
